eth_bip32-0.1.1.dist-info/LICENSE
eth_bip32-0.1.1.dist-info/WHEEL
eth_bip32-0.1.1.dist-info/top_level.txt
eth_bip32-0.1.1.dist-info/RECORD
eth_bip32-0.1.1.dist-info/METADATA
eth_bip32/hdwallet.py
eth_bip32/__init__.py
eth_bip32/keccak/keccak256_module.c
eth_bip32/keccak/_keccak256.cpython-310-x86_64-linux-gnu.so
eth_bip32/keccak/keccak256.c
eth_bip32/keccak/keccak256.h
eth_bip32/keccak/__init__.py
