Metadata-Version: 2.1
Name: eth_bip32
Version: 0.1.1
Summary: Ethereum BIP32 HD Wallet implementation
Author: Mate Dravucz
License: MIT
Project-URL: Homepage, https://github.com/mattdravucz/eth-bip32
Project-URL: Issues, https://github.com/mattdravucz/eth-bip32/issues
Classifier: Programming Language :: Python :: 3
Classifier: Programming Language :: Python :: 3.9
Classifier: Programming Language :: Python :: 3.11
Classifier: License :: OSI Approved :: MIT License
Classifier: Operating System :: OS Independent
Classifier: Operating System :: POSIX :: Linux
Classifier: Operating System :: Microsoft :: Windows
Classifier: Operating System :: MacOS :: MacOS X
License-File: LICENSE
Requires-Dist: ecdsa
